fastcrc-0.3.5.dist-info/METADATA
fastcrc-0.3.5.dist-info/WHEEL
fastcrc-0.3.5.dist-info/licenses/LICENSE
fastcrc.libs/libgcc_s-6d2d9dc8.so.1
fastcrc/__info__.py
fastcrc/__init__.py
fastcrc/crc16.py
fastcrc/crc32.py
fastcrc/crc64.py
fastcrc/crc8.py
fastcrc/fastcrc.cpython-310-x86_64-linux-gnu.so
fastcrc/py.typed
fastcrc-0.3.5.dist-info/RECORD
