Metadata-Version: 2.4
Name: fastcrc
Version: 0.3.5
Classifier: Development Status :: 4 - Beta
Classifier: Intended Audience :: Developers
Classifier: License :: OSI Approved :: MIT License
Classifier: Operating System :: MacOS
Classifier: Operating System :: Microsoft :: Windows
Classifier: Operating System :: POSIX :: Linux
Classifier: Programming Language :: Rust
Classifier: Programming Language :: Python :: Implementation :: CPython
Classifier: Programming Language :: Python :: Implementation :: PyPy
Classifier: Topic :: Software Development :: Libraries :: Python Modules
Classifier: Typing :: Typed
License-File: LICENSE
Summary: A hyper-fast Python module for computing CRC(8, 16, 32, 64) checksum
Keywords: crc,crc8,crc16,crc32,crc64
Home-Page: https://github.com/overcat/fastcrc
Author-email: overcat <4catcode@gmail.com>
Requires-Python: >=3.7
Project-URL: homepage, https://github.com/overcat/fastcrc
Project-URL: repository, https://github.com/overcat/fastcrc
Project-URL: documentation, https://fastcrc.readthedocs.io
